vuray/__init__.py
vuray/api.py
vuray/cli.py
vuray/utils.py
vuray-0.0.1.dist-info/METADATA
vuray-0.0.1.dist-info/RECORD
vuray-0.0.1.dist-info/WHEEL
vuray-0.0.1.dist-info/entry_points.txt
vuray-0.0.1.dist-info/top_level.txt
